mcp_server_mongodb/__init__.py
mcp_server_mongodb/server.py
mcp_server_mongodb/resource/__init__.py
mcp_server_mongodb/resource/mongo_resource.py
mongodb_mcp_server-0.1.1.dist-info/METADATA
mongodb_mcp_server-0.1.1.dist-info/WHEEL
mongodb_mcp_server-0.1.1.dist-info/entry_points.txt
mongodb_mcp_server-0.1.1.dist-info/top_level.txt
mongodb_mcp_server-0.1.1.dist-info/RECORD
