Metadata-Version: 2.4
Name: mongodb-mcp-server
Version: 0.1.1
Summary: Add your description here
Requires-Python: >=3.13
Requires-Dist: mcp[cli]
Requires-Dist: volcengine-python-sdk
